{
    "swagger": "2.0",
    "info": {
        "description": "API documentation for Shopping Service",
        "title": "Shopping Service API",
        "contact": {},
        "version": "1.0"
    },
    "host": "localhost:8080",
    "basePath": "/",
    "paths": {
        "/products": {
            "get": {
                "description": "Retrieve all products from the database",
                "produces": [
                    "application/json"
                ],
                "tags": [
                    "products"
                ],
                "summary": "Get all products",
                "responses": {
                    "200": {
                        "description": "OK",
                        "schema": {
                            "$ref": "#/definitions/controllers.SuccessResponse"
                        }
                    },
                    "500": {
                        "description": "Internal Server Error",
                        "schema": {
                            "$ref": "#/definitions/controllers.ErrorResponse"
                        }
                    }
                }
            },
            "post": {
                "description": "Add a new product to the database",
                "consumes": [
                    "application/json"
                ],
                "produces": [
                    "application/json"
                ],
                "tags": [
                    "products"
                ],
                "summary": "Create a new product",
                "parameters": [
                    {
                        "description": "Product data",
                        "name": "product",
                        "in": "body",
                        "required": true,
                        "schema": {
                            "$ref": "#/definitions/models.ProductRequest"
                        }
                    }
                ],
                "responses": {
                    "201": {
                        "description": "Created",
                        "schema": {
                            "$ref": "#/definitions/controllers.SuccessResponse"
                        }
                    },
                    "400": {
                        "description": "Bad Request",
                        "schema": {
                            "$ref": "#/definitions/controllers.ErrorResponse"
                        }
                    },
                    "500": {
                        "description": "Internal Server Error",
                        "schema": {
                            "$ref": "#/definitions/controllers.ErrorResponse"
                        }
                    }
                }
            }
        },
        "/products/{id}": {
            "get": {
                "description": "Retrieve a product by its ID",
                "produces": [
                    "application/json"
                ],
                "tags": [
                    "products"
                ],
                "summary": "Get product by ID",
                "parameters": [
                    {
                        "type": "string",
                        "description": "Product ID",
                        "name": "id",
                        "in": "path",
                        "required": true
                    }
                ],
                "responses": {
                    "200": {
                        "description": "OK",
                        "schema": {
                            "$ref": "#/definitions/controllers.SuccessResponse"
                        }
                    },
                    "404": {
                        "description": "Not Found",
                        "schema": {
                            "$ref": "#/definitions/controllers.ErrorResponse"
                        }
                    }
                }
            },
            "put": {
                "description": "Update an existing product by its ID",
                "consumes": [
                    "application/json"
                ],
                "produces": [
                    "application/json"
                ],
                "tags": [
                    "products"
                ],
                "summary": "Update a product",
                "parameters": [
                    {
                        "type": "string",
                        "description": "Product ID",
                        "name": "id",
                        "in": "path",
                        "required": true
                    },
                    {
                        "description": "Product data",
                        "name": "product",
                        "in": "body",
                        "required": true,
                        "schema": {
                            "$ref": "#/definitions/models.ProductRequest"
                        }
                    }
                ],
                "responses": {
                    "200": {
                        "description": "OK",
                        "schema": {
                            "$ref": "#/definitions/controllers.SuccessResponse"
                        }
                    },
                    "400": {
                        "description": "Bad Request",
                        "schema": {
                            "$ref": "#/definitions/controllers.ErrorResponse"
                        }
                    },
                    "500": {
                        "description": "Internal Server Error",
                        "schema": {
                            "$ref": "#/definitions/controllers.ErrorResponse"
                        }
                    }
                }
            },
            "delete": {
                "description": "Delete a product by its ID",
                "produces": [
                    "application/json"
                ],
                "tags": [
                    "products"
                ],
                "summary": "Delete a product",
                "parameters": [
                    {
                        "type": "string",
                        "description": "Product ID",
                        "name": "id",
                        "in": "path",
                        "required": true
                    }
                ],
                "responses": {
                    "200": {
                        "description": "OK",
                        "schema": {
                            "$ref": "#/definitions/controllers.SuccessResponse"
                        }
                    },
                    "500": {
                        "description": "Internal Server Error",
                        "schema": {
                            "$ref": "#/definitions/controllers.ErrorResponse"
                        }
                    }
                }
            }
        },
        "/transactions": {
            "get": {
                "description": "Retrieve all transactions from the database",
                "produces": [
                    "application/json"
                ],
                "tags": [
                    "transactions"
                ],
                "summary": "Get all transactions",
                "responses": {
                    "200": {
                        "description": "OK",
                        "schema": {
                            "$ref": "#/definitions/controllers.SuccessResponse"
                        }
                    },
                    "500": {
                        "description": "Internal Server Error",
                        "schema": {
                            "$ref": "#/definitions/controllers.ErrorResponse"
                        }
                    }
                }
            },
            "post": {
                "description": "Add a new transaction to the database",
                "consumes": [
                    "application/json"
                ],
                "produces": [
                    "application/json"
                ],
                "tags": [
                    "transactions"
                ],
                "summary": "Create a new transaction",
                "parameters": [
                    {
                        "description": "Transaction data (must include product_id)",
                        "name": "transaction",
                        "in": "body",
                        "required": true,
                        "schema": {
                            "$ref": "#/definitions/models.TransactionRequest"
                        }
                    }
                ],
                "responses": {
                    "201": {
                        "description": "Created",
                        "schema": {
                            "$ref": "#/definitions/controllers.SuccessResponse"
                        }
                    },
                    "400": {
                        "description": "Bad Request",
                        "schema": {
                            "$ref": "#/definitions/controllers.ErrorResponse"
                        }
                    },
                    "500": {
                        "description": "Internal Server Error",
                        "schema": {
                            "$ref": "#/definitions/controllers.ErrorResponse"
                        }
                    }
                }
            }
        },
        "/transactions/{id}": {
            "get": {
                "description": "Retrieve a transaction by its ID",
                "produces": [
                    "application/json"
                ],
                "tags": [
                    "transactions"
                ],
                "summary": "Get transaction by ID",
                "parameters": [
                    {
                        "type": "string",
                        "description": "Transaction ID",
                        "name": "id",
                        "in": "path",
                        "required": true
                    }
                ],
                "responses": {
                    "200": {
                        "description": "OK",
                        "schema": {
                            "$ref": "#/definitions/controllers.SuccessResponse"
                        }
                    },
                    "404": {
                        "description": "Not Found",
                        "schema": {
                            "$ref": "#/definitions/controllers.ErrorResponse"
                        }
                    }
                }
            },
            "put": {
                "description": "Update an existing transaction by its ID",
                "consumes": [
                    "application/json"
                ],
                "produces": [
                    "application/json"
                ],
                "tags": [
                    "transactions"
                ],
                "summary": "Update a transaction",
                "parameters": [
                    {
                        "type": "string",
                        "description": "Transaction ID",
                        "name": "id",
                        "in": "path",
                        "required": true
                    },
                    {
                        "description": "Transaction data (can include product_id)",
                        "name": "transaction",
                        "in": "body",
                        "required": true,
                        "schema": {
                            "$ref": "#/definitions/models.TransactionUpdateRequest"
                        }
                    }
                ],
                "responses": {
                    "200": {
                        "description": "OK",
                        "schema": {
                            "$ref": "#/definitions/controllers.SuccessResponse"
                        }
                    },
                    "400": {
                        "description": "Bad Request",
                        "schema": {
                            "$ref": "#/definitions/controllers.ErrorResponse"
                        }
                    },
                    "500": {
                        "description": "Internal Server Error",
                        "schema": {
                            "$ref": "#/definitions/controllers.ErrorResponse"
                        }
                    }
                }
            },
            "delete": {
                "description": "Delete a transaction by its ID",
                "produces": [
                    "application/json"
                ],
                "tags": [
                    "transactions"
                ],
                "summary": "Delete a transaction",
                "parameters": [
                    {
                        "type": "string",
                        "description": "Transaction ID",
                        "name": "id",
                        "in": "path",
                        "required": true
                    }
                ],
                "responses": {
                    "200": {
                        "description": "OK",
                        "schema": {
                            "$ref": "#/definitions/controllers.SuccessResponse"
                        }
                    },
                    "500": {
                        "description": "Internal Server Error",
                        "schema": {
                            "$ref": "#/definitions/controllers.ErrorResponse"
                        }
                    }
                }
            }
        }
    },
    "definitions": {
        "controllers.ErrorResponse": {
            "type": "object",
            "properties": {
                "error": {
                    "type": "string"
                },
                "message": {
                    "type": "string"
                }
            }
        },
        "controllers.SuccessResponse": {
            "type": "object",
            "properties": {
                "data": {},
                "message": {
                    "type": "string"
                }
            }
        },
        "models.ProductRequest": {
            "type": "object",
            "required": [
                "name",
                "price"
            ],
            "properties": {
                "name": {
                    "type": "string"
                },
                "price": {
                    "type": "number"
                }
            }
        },
        "models.TransactionRequest": {
            "type": "object",
            "required": [
                "payment_method",
                "price",
                "product_id"
            ],
            "properties": {
                "payment_method": {
                    "type": "string"
                },
                "price": {
                    "type": "number"
                },
                "product_id": {
                    "type": "string"
                }
            }
        },
        "models.TransactionUpdateRequest": {
            "type": "object",
            "properties": {
                "payment_method": {
                    "type": "string"
                },
                "price": {
                    "type": "number"
                },
                "product_id": {
                    "type": "string"
                }
            }
        }
    }
}